LICENSE
README.md
setup.cfg
setup.py
py_md_doc/__init__.py
py_md_doc/class_inheritance.py
py_md_doc/doc_base.py
py_md_doc/parameter.py
py_md_doc/py_md_doc.py
py_md_doc/var_doc.py
py_md_doc.egg-info/PKG-INFO
py_md_doc.egg-info/SOURCES.txt
py_md_doc.egg-info/dependency_links.txt
py_md_doc.egg-info/top_level.txt