Metadata-Version: 2.1
Name: py-md-doc
Version: 0.5.1
Summary: Generate markdown documentation for your Python scripts.Like Sphinx, but simpler and directly compatible with GitHub.
Home-page: https://github.com/subalterngames/py_md_doc
Download-URL: https://github.com/subalterngames/py_md_doc/archive/0.1.tar.gz
Author: Seth Alter
Author-email: subalterngames@gmail.com
License: MIT
Keywords: documentation,doc,sphinx,markdown,github
Classifier: Development Status :: 5 - Production/Stable
Classifier: Intended Audience :: Developers
Classifier: Topic :: Software Development
Classifier: License :: OSI Approved :: MIT License
Classifier: Programming Language :: Python :: 3.6
Classifier: Programming Language :: Python :: 3.7
Classifier: Programming Language :: Python :: 3.8
Classifier: Programming Language :: Python :: 3.9
Classifier: Programming Language :: Python :: 3.10
Classifier: Programming Language :: Python :: 3.11
Classifier: Programming Language :: Python :: 3.12
License-File: LICENSE
